<?xml version="1.0" encoding="utf-8"?><CatapultTargetIndex><IndexEntry><Entries><IndexEntry Term="mastication (change agent)"><Entries /><Links><IndexLink Title="Change Agents" Link="/Content/08-FERA-Tools/FERA-FCCS-ChangeAgentsTable.htm#kanchor1216" UsedConditions="" LocalConditions="" /></Links><SeeAlsoLinks /><IndexControlLinks /><SortAsLinks /></IndexEntry><IndexEntry Term="Maximum Fire Width (parameter)"><Entries /><Links><IndexLink Title="Surface Fire Size Output Parameters" Link="/Content/10-Reference/RefSIZEOut.htm#kanchor1052" UsedConditions="" LocalConditions="" /></Links><SeeAlsoLinks /><IndexControlLinks /><SortAsLinks /></IndexEntry><IndexEntry Term="Maximum Plume Height (parameter)"><Entries><IndexEntry Term="FEPS output"><Entries /><Links><IndexLink Title="Output Parameters—Hourly Consumption and Emissions Data" Link="/Content/08-FERA-Tools/FERA-FEPS-Out-Consumption.htm#kanchor410" UsedConditions="" LocalConditions="" /></Links><SeeAlsoLinks /><IndexControlLinks /><SortAsLinks /></IndexEntry><IndexEntry Term="in exported file"><Entries /><Links><IndexLink Title="Exported Hourly Consumption and Emissions Parameters" Link="/Content/08-FERA-Tools/FERA-FEPS-Out-CSV.htm#kanchor883" UsedConditions="" LocalConditions="" /></Links><SeeAlsoLinks /><IndexControlLinks /><SortAsLinks /></IndexEntry></Entries><Links /><SeeAlsoLinks /><IndexControlLinks /><SortAsLinks /></IndexEntry><IndexEntry Term="medium flame length" ReferenceTerms="flame lengths" Reference="See"><Entries><IndexEntry Term="flame lengths" GeneratedReferenceType="See"><Entries /><Links /><SeeAlsoLinks /><IndexControlLinks /><SortAsLinks /></IndexEntry></Entries><Links /><SeeAlsoLinks /><IndexControlLinks /><SortAsLinks /></IndexEntry><IndexEntry Term="Medium Flame Lengths (parameter)"><Entries /><Links><IndexLink Title="Input Parameters" Link="/Content/10-Reference/RefRANIn.htm#kanchor290" UsedConditions="" LocalConditions="" /><IndexLink Title="Input Parameters" Link="/Content/10-Reference/RefRiskWorstIn.htm#kanchor313" UsedConditions="" LocalConditions="" /><IndexLink Title="Hazard Workflow" Link="/Content/05-Hazard-Analysis/HazardWorkflow.htm#kanchor562" UsedConditions="" LocalConditions="" /><IndexLink Title="Input Parameters" Link="/Content/10-Reference/RefRiskFLIn.htm#kanchor623" UsedConditions="" LocalConditions="" /><IndexLink Title="Risk Assessment Workflow" Link="/Content/06-Risk-Assessment/RiskAssessWorkflow.htm#kanchor1010" UsedConditions="" LocalConditions="" /><IndexLink Title="Risk Assessment Workflow" Link="/Content/06-Risk-Assessment/RiskAssessWorkflow.htm#kanchor1029" UsedConditions="" LocalConditions="" /><IndexLink Title="Fuels Treatment Workflow" Link="/Content/07-FuelsTreatment/FuelsTreatWorkflow.htm#kanchor1130" UsedConditions="" LocalConditions="" /><IndexLink Title="Fuels Treatment Workflow" Link="/Content/07-FuelsTreatment/FuelsTreatWorkflow.htm#kanchor1148" UsedConditions="" LocalConditions="" /></Links><SeeAlsoLinks /><IndexControlLinks /><SortAsLinks /></IndexEntry><IndexEntry Term="medium logging slash (fire behavior fuel model FM 12)"><Entries /><Links><IndexLink Title="Fire Behavior Fuel Models and Their Environments" Link="/Content/10-Reference/RefFuelModels.htm#kanchor798" UsedConditions="" LocalConditions="" /></Links><SeeAlsoLinks /><IndexControlLinks /><SortAsLinks /></IndexEntry><IndexEntry Term="methane"><Entries><IndexEntry Term="FEPS input"><Entries /><Links><IndexLink Title="Input Parameters—Consumption and Emissions Data" Link="/Content/08-FERA-Tools/FERA-FEPS-In-Consumption.htm#kanchor208" UsedConditions="" LocalConditions="" /></Links><SeeAlsoLinks /><IndexControlLinks /><SortAsLinks /></IndexEntry></Entries><Links /><SeeAlsoLinks /><IndexControlLinks /><SortAsLinks /></IndexEntry><IndexEntry Term="metric units of measure"><Entries /><Links><IndexLink Title="Universal" Link="/Content/10-Reference/Universal.htm#kanchor108" UsedConditions="" LocalConditions="" /></Links><SeeAlsoLinks /><IndexControlLinks /><SortAsLinks /></IndexEntry><IndexEntry Term="Mid-flame Wind Speed (parameter)"><Entries /><Links><IndexLink Title="Hazard Workflow" Link="/Content/05-Hazard-Analysis/HazardWorkflow.htm#kanchor587" UsedConditions="" LocalConditions="" /><IndexLink Title="Output Parameters (Surface Fire Behavior as Implemented in FlamMap)" Link="/Content/10-Reference/RefFlamMapOut.htm#kanchor855" UsedConditions="" LocalConditions="" /><IndexLink Title="Fuels Treatment Workflow" Link="/Content/07-FuelsTreatment/FuelsTreatWorkflow.htm#kanchor1098" UsedConditions="" LocalConditions="" /></Links><SeeAlsoLinks /><IndexControlLinks /><SortAsLinks /></IndexEntry><IndexEntry Term="Midday Time (parameter)"><Entries /><Links><IndexLink Title="Input Parameters—Environmental" Link="/Content/08-FERA-Tools/FERA-FEPS-In-Environment.htm#kanchor953" UsedConditions="" LocalConditions="" /></Links><SeeAlsoLinks /><IndexControlLinks /><SortAsLinks /></IndexEntry><IndexEntry Term="Midflame Wind Speed - Maximum (parameter)"><Entries /><Links><IndexLink Title="Input Parameters—Environmental" Link="/Content/08-FERA-Tools/FERA-FEPS-In-Environment.htm#kanchor959" UsedConditions="" LocalConditions="" /></Links><SeeAlsoLinks /><IndexControlLinks /><SortAsLinks /></IndexEntry><IndexEntry Term="Midflame Wind Speed - Minimum (parameter)"><Entries /><Links><IndexLink Title="Input Parameters—Environmental" Link="/Content/08-FERA-Tools/FERA-FEPS-In-Environment.htm#kanchor960" UsedConditions="" LocalConditions="" /></Links><SeeAlsoLinks /><IndexControlLinks /><SortAsLinks /></IndexEntry><IndexEntry Term="Midflame wind speed (option)"><Entries /><Links><IndexLink Title="Surface Fire Spread and Intensity Input Options –  Wind Speed" Link="/Content/10-Reference/RefSURFInOptWind.htm#kanchor1179" UsedConditions="" LocalConditions="" /></Links><SeeAlsoLinks /><IndexControlLinks /><SortAsLinks /></IndexEntry><IndexEntry Term="Midflame Wind Speed (parameter)"><Entries /><Links><IndexLink Title="FCCS Surface Fire Behavior Input tbls EMB" Link="/Content/08-FERA-Tools/FERA-FCCS-SFB-SurfaceFireBehaviorInput.htm#kanchor156" UsedConditions="" LocalConditions="" /><IndexLink Title="Input Parameters – Fuel Consumption for Activity Fuels" Link="/Content/08-FERA-Tools/FERA-Consume-ActivityFuelsFuelConsumptionIn.htm#kanchor264" UsedConditions="" LocalConditions="" /><IndexLink Title="Intermediate Parameters—Hourly Meteorological Data" Link="/Content/08-FERA-Tools/FERA-FEPS-Intermediate.htm#kanchor741" UsedConditions="" LocalConditions="" /></Links><SeeAlsoLinks /><IndexControlLinks /><SortAsLinks /></IndexEntry><IndexEntry Term="Midflame Wind Speed (upslope) (parameter)"><Entries /><Links><IndexLink Title="Crown Scorch Height Input Parameters" Link="/Content/10-Reference/RefSCORCHIn.htm#kanchor703" UsedConditions="" LocalConditions="" /></Links><SeeAlsoLinks /><IndexControlLinks /><SortAsLinks /></IndexEntry><IndexEntry Term="Minimum Plume Height (parameter)"><Entries><IndexEntry Term="FEPS output"><Entries /><Links><IndexLink Title="Output Parameters—Hourly Consumption and Emissions Data" Link="/Content/08-FERA-Tools/FERA-FEPS-Out-Consumption.htm#kanchor411" UsedConditions="" LocalConditions="" /></Links><SeeAlsoLinks /><IndexControlLinks /><SortAsLinks /></IndexEntry><IndexEntry Term="in exported file"><Entries /><Links><IndexLink Title="Exported Hourly Consumption and Emissions Parameters" Link="/Content/08-FERA-Tools/FERA-FEPS-Out-CSV.htm#kanchor884" UsedConditions="" LocalConditions="" /></Links><SeeAlsoLinks /><IndexControlLinks /><SortAsLinks /></IndexEntry></Entries><Links /><SeeAlsoLinks /><IndexControlLinks /><SortAsLinks /></IndexEntry><IndexEntry Term="minimum travel time" ReferenceTerms="fire behavior (MTT)" Reference="See"><Entries><IndexEntry Term="fire behavior (MTT)" GeneratedReferenceType="See"><Entries /><Links /><SeeAlsoLinks /><IndexControlLinks /><SortAsLinks /></IndexEntry></Entries><Links /><SeeAlsoLinks /><IndexControlLinks /><SortAsLinks /></IndexEntry><IndexEntry Term="mixed forests"><Entries><IndexEntry Term="fuelbeds and"><Entries /><Links><IndexLink Title="Vegetation Forms" Link="/Content/08-FERA-Tools/FERA-Fuelbed-Veg.htm#kanchor1174" UsedConditions="" LocalConditions="" /></Links><SeeAlsoLinks /><IndexControlLinks /><SortAsLinks /></IndexEntry></Entries><Links /><SeeAlsoLinks /><IndexControlLinks /><SortAsLinks /></IndexEntry><IndexEntry Term="modules"><Entries><IndexEntry Term="consumption, emissions, and heat release (Consume)"><Entries /><Links><IndexLink Title="Consumption, Emissions, and Heat Release (Consume)" Link="/Content/10-Reference/RefCONSUME.htm#kanchor858" UsedConditions="" LocalConditions="" /></Links><SeeAlsoLinks /><IndexControlLinks /><SortAsLinks /></IndexEntry><IndexEntry Term="containment resources"><Entries /><Links><IndexLink Title="Containment Resources (IFT-contain)" Link="/Content/10-Reference/RefCONTAIN.htm#kanchor277" UsedConditions="" LocalConditions="" /></Links><SeeAlsoLinks /><IndexControlLinks /><SortAsLinks /></IndexEntry><IndexEntry Term="data input"><Entries /><Links><IndexLink Title="Creating a New Run" Link="/Content/03-Concepts/ProjRun.htm#kanchor455" UsedConditions="" LocalConditions="" /><IndexLink Title="Data Sets and Data Management" Link="/Content/03-Concepts/DataSets.htm#kanchor1199" UsedConditions="" LocalConditions="" /></Links><SeeAlsoLinks /><IndexControlLinks /><SortAsLinks /></IndexEntry><IndexEntry Term="data output"><Entries /><Links><IndexLink Title="Creating a New Run" Link="/Content/03-Concepts/ProjRun.htm#kanchor457" UsedConditions="" LocalConditions="" /><IndexLink Title="Data Sets and Data Management" Link="/Content/03-Concepts/DataSets.htm#kanchor1199" UsedConditions="" LocalConditions="" /></Links><SeeAlsoLinks /><IndexControlLinks /><SortAsLinks /></IndexEntry><IndexEntry Term="elliptical fire shape"><Entries /><Links><IndexLink Title="Surface Fire Size Output Parameters" Link="/Content/10-Reference/RefSIZEOut.htm#kanchor1045" UsedConditions="" LocalConditions="" /></Links><SeeAlsoLinks /><IndexControlLinks /><SortAsLinks /></IndexEntry><IndexEntry Term="fire behavior fuel"><Entries><IndexEntry Term="supported types"><Entries /><Links><IndexLink Title="Landscape Data Parameters" Link="/Content/10-Reference/RefRiskWorstCaseLandscape.htm#kanchor334" UsedConditions="" LocalConditions="" /><IndexLink Title="Landscape Data Parameters" Link="/Content/10-Reference/RefRiskFL-Landscape.htm#kanchor483" UsedConditions="" LocalConditions="" /><IndexLink Title="Landscape Data Parameters" Link="/Content/10-Reference/RefRANLandscape.htm#kanchor926" UsedConditions="" LocalConditions="" /><IndexLink Title="Landscape Data Parameters" Link="/Content/10-Reference/RefFlamMapLandscape.htm#kanchor1236" UsedConditions="" LocalConditions="" /></Links><SeeAlsoLinks /><IndexControlLinks /><SortAsLinks /></IndexEntry></Entries><Links /><SeeAlsoLinks /><IndexControlLinks /><SortAsLinks /></IndexEntry><IndexEntry Term="graph view"><Entries /><Links><IndexLink Title="Creating a New Run" Link="/Content/03-Concepts/ProjRun.htm#kanchor460" UsedConditions="" LocalConditions="" /></Links><SeeAlsoLinks /><IndexControlLinks /><SortAsLinks /></IndexEntry><IndexEntry Term="hazard analysis"><Entries /><Links><IndexLink Title="Modules for Hazard Analysis" Link="/Content/03-Concepts/ModelsHazard.htm#kanchor4" UsedConditions="" LocalConditions="" /></Links><SeeAlsoLinks /><IndexControlLinks /><SortAsLinks /></IndexEntry><IndexEntry Term="input forms"><Entries><IndexEntry Term="default values"><Entries /><Links><IndexLink Title="Creating a New Run" Link="/Content/03-Concepts/ProjRun.htm#kanchor456" UsedConditions="" LocalConditions="" /></Links><SeeAlsoLinks /><IndexControlLinks /><SortAsLinks /></IndexEntry></Entries><Links /><SeeAlsoLinks /><IndexControlLinks /><SortAsLinks /></IndexEntry><IndexEntry Term="map view"><Entries /><Links><IndexLink Title="Creating a New Run" Link="/Content/03-Concepts/ProjRun.htm#kanchor462" UsedConditions="" LocalConditions="" /></Links><SeeAlsoLinks /><IndexControlLinks /><SortAsLinks /></IndexEntry><IndexEntry Term="model configuration"><Entries /><Links><IndexLink Title="Creating a New Run" Link="/Content/03-Concepts/ProjRun.htm#kanchor454" UsedConditions="" LocalConditions="" /></Links><SeeAlsoLinks /><IndexControlLinks /><SortAsLinks /></IndexEntry><IndexEntry Term="overview"><Entries /><Links><IndexLink Title="Overview of the Modules in IFTDSS" Link="/Content/03-Concepts/Models.htm#kanchor1175" UsedConditions="" LocalConditions="" /></Links><SeeAlsoLinks /><IndexControlLinks /><SortAsLinks /></IndexEntry><IndexEntry Term="prescribed burn plans"><Entries /><Links><IndexLink Title="Modules for Prescribed Burn Planning" Link="/Content/03-Concepts/ModelsRx.htm#kanchor1067" UsedConditions="" LocalConditions="" /></Links><SeeAlsoLinks /><IndexControlLinks /><SortAsLinks /></IndexEntry><IndexEntry Term="runs"><Entries><IndexEntry Term="summary page"><Entries /><Links><IndexLink Title="Creating a New Run" Link="/Content/03-Concepts/ProjRun.htm#kanchor468" UsedConditions="" LocalConditions="" /></Links><SeeAlsoLinks /><IndexControlLinks /><SortAsLinks /></IndexEntry></Entries><Links /><SeeAlsoLinks /><IndexControlLinks /><SortAsLinks /></IndexEntry><IndexEntry Term="table view"><Entries /><Links><IndexLink Title="Creating a New Run" Link="/Content/03-Concepts/ProjRun.htm#kanchor459" UsedConditions="" LocalConditions="" /></Links><SeeAlsoLinks /><IndexControlLinks /><SortAsLinks /></IndexEntry><IndexEntry Term="test cases"><Entries /><Links><IndexLink Title="Module Test Cases" Link="/Content/10-Reference/RefModelTests.htm#kanchor122" UsedConditions="" LocalConditions="" /></Links><SeeAlsoLinks /><IndexControlLinks /><SortAsLinks /></IndexEntry></Entries><Links /><SeeAlsoLinks /><IndexControlLinks /><SortAsLinks /></IndexEntry><IndexEntry Term="moisture"><Entries><IndexEntry Term="estimating in live fuel"><Entries /><Links><IndexLink Title="Estimating Live Fuel Moisture" Link="/Content/10-Reference/RefFuelModelsMoistureandCuring.htm#kanchor745" UsedConditions="" LocalConditions="" /></Links><SeeAlsoLinks /><IndexControlLinks /><SortAsLinks /></IndexEntry><IndexEntry Term="fire behavior fuel models and"><Entries /><Links><IndexLink Title="Moisture Inputs for Fire Behavior Fuel&#160;Models" Link="/Content/10-Reference/RefFuelModelsMoisture.htm#kanchor92" UsedConditions="" LocalConditions="" /></Links><SeeAlsoLinks /><IndexControlLinks /><SortAsLinks /></IndexEntry><IndexEntry Term="level of curing and"><Entries /><Links><IndexLink Title="Estimating Live Fuel Moisture" Link="/Content/10-Reference/RefFuelModelsMoistureandCuring.htm#kanchor745" UsedConditions="" LocalConditions="" /></Links><SeeAlsoLinks /><IndexControlLinks /><SortAsLinks /></IndexEntry><IndexEntry Term="surface fires and"><Entries /><Links><IndexLink Title="Surface Fire Spread and Intensity Input Options –  Moisture" Link="/Content/10-Reference/RefSURFInOptMoisture.htm#kanchor995" UsedConditions="" LocalConditions="" /></Links><SeeAlsoLinks /><IndexControlLinks /><SortAsLinks /></IndexEntry></Entries><Links /><SeeAlsoLinks /><IndexControlLinks /><SortAsLinks /></IndexEntry><IndexEntry Term="Moisture is entered (option)"><Entries /><Links><IndexLink Title="Surface Fire Spread and Intensity Input Options –  Moisture" Link="/Content/10-Reference/RefSURFInOptMoisture.htm#kanchor998" UsedConditions="" LocalConditions="" /></Links><SeeAlsoLinks /><IndexControlLinks /><SortAsLinks /></IndexEntry><IndexEntry Term="Moisture of 1000-hr Fuels (parameter)"><Entries /><Links><IndexLink Title="Populating and running the IFT-Consume model" Link="/Content/13-Effects_2015/Consume_smoke/IFT_consume_effects_4.htm#kanchor177" UsedConditions="" LocalConditions="" /><IndexLink Title="Consumption and Emissions (Consume)&#160;Input Parameters" Link="/Content/10-Reference/RefConIn.htm#kanchor248" UsedConditions="" LocalConditions="" /></Links><SeeAlsoLinks /><IndexControlLinks /><SortAsLinks /></IndexEntry><IndexEntry Term="Moisture Scenario (parameter)"><Entries /><Links><IndexLink Title="FCCS Surface Fire Behavior Input tbls EMB" Link="/Content/08-FERA-Tools/FERA-FCCS-SFB-SurfaceFireBehaviorInput.htm#kanchor145" UsedConditions="" LocalConditions="" /></Links><SeeAlsoLinks /><IndexControlLinks /><SortAsLinks /></IndexEntry><IndexEntry Term="moisture scenarios"><Entries><IndexEntry Term="uncured 1000-hour woody fuel"><Entries /><Links><IndexLink Title="Estimations for Uncured 1000-Hour Woody Fuel Moisture" Link="/Content/08-FERA-Tools/FERA-Consume-Activity-Uncured-Woody.htm#kanchor1167" UsedConditions="" LocalConditions="" /></Links><SeeAlsoLinks /><IndexControlLinks /><SortAsLinks /></IndexEntry></Entries><Links /><SeeAlsoLinks /><IndexControlLinks /><SortAsLinks /></IndexEntry><IndexEntry Term="MORTALITY (BehavePlus)"><Entries /><Links><IndexLink Title="BehavePlus Functionality available in IFTDSS Version 1 0" Link="/Content/11-Comparing-IFTDSS/IFTCompare-BehavePlus.htm#kanchor193" UsedConditions="" LocalConditions="" /></Links><SeeAlsoLinks /><IndexControlLinks /><SortAsLinks /></IndexEntry><IndexEntry Term="MTT" ReferenceTerms="fire behavior (MTT)" Reference="See"><Entries><IndexEntry Term="fire behavior (MTT)" GeneratedReferenceType="See"><Entries /><Links /><SeeAlsoLinks /><IndexControlLinks /><SortAsLinks /></IndexEntry></Entries><Links /><SeeAlsoLinks /><IndexControlLinks /><SortAsLinks /></IndexEntry><IndexEntry Term="natural events (change agent)"><Entries /><Links><IndexLink Title="Change Agents" Link="/Content/08-FERA-Tools/FERA-FCCS-ChangeAgentsTable.htm#kanchor1219" UsedConditions="" LocalConditions="" /></Links><SeeAlsoLinks /><IndexControlLinks /><SortAsLinks /></IndexEntry><IndexEntry Term="NB1"><Entries /><Links><IndexLink Title="Fire Behavior Fuel Models and Their Environments" Link="/Content/10-Reference/RefFuelModels.htm#kanchor800" UsedConditions="" LocalConditions="" /></Links><SeeAlsoLinks /><IndexControlLinks /><SortAsLinks /></IndexEntry><IndexEntry Term="NB2"><Entries /><Links><IndexLink Title="Fire Behavior Fuel Models and Their Environments" Link="/Content/10-Reference/RefFuelModels.htm#kanchor801" UsedConditions="" LocalConditions="" /></Links><SeeAlsoLinks /><IndexControlLinks /><SortAsLinks /></IndexEntry><IndexEntry Term="NB3"><Entries /><Links><IndexLink Title="Fire Behavior Fuel Models and Their Environments" Link="/Content/10-Reference/RefFuelModels.htm#kanchor802" UsedConditions="" LocalConditions="" /></Links><SeeAlsoLinks /><IndexControlLinks /><SortAsLinks /></IndexEntry><IndexEntry Term="NB8"><Entries /><Links><IndexLink Title="Fire Behavior Fuel Models and Their Environments" Link="/Content/10-Reference/RefFuelModels.htm#kanchor803" UsedConditions="" LocalConditions="" /></Links><SeeAlsoLinks /><IndexControlLinks /><SortAsLinks /></IndexEntry><IndexEntry Term="NB9"><Entries /><Links><IndexLink Title="Fire Behavior Fuel Models and Their Environments" Link="/Content/10-Reference/RefFuelModels.htm#kanchor804" UsedConditions="" LocalConditions="" /></Links><SeeAlsoLinks /><IndexControlLinks /><SortAsLinks /></IndexEntry><IndexEntry Term="net value change" ReferenceTerms="values at risk" Reference="SeeAlso"><Entries><IndexEntry Term="values at risk" GeneratedReferenceType="SeeAlso"><Entries /><Links /><SeeAlsoLinks /><IndexControlLinks /><SortAsLinks /></IndexEntry><IndexEntry Term="calculating"><Entries /><Links><IndexLink Title="Example Using the Flame Length Probabilities Approach" Link="/Content/06-Risk-Assessment/risk_original/RiskAssessNetValueChange3.htm#kanchor1194" UsedConditions="" LocalConditions="" /></Links><SeeAlsoLinks /><IndexControlLinks /><SortAsLinks /></IndexEntry><IndexEntry Term="flame length probabilities example"><Entries /><Links><IndexLink Title="Example Using the Flame Length Probabilities Approach" Link="/Content/06-Risk-Assessment/risk_original/RiskAssessNetValueChange3.htm#kanchor1193" UsedConditions="" LocalConditions="" /></Links><SeeAlsoLinks /><IndexControlLinks /><SortAsLinks /></IndexEntry><IndexEntry Term="multiplier"><Entries /><Links><IndexLink Title="Risk Assessment Glossary" Link="/Content/06-Risk-Assessment/risk_original/RiskAssessGlossary.htm#kanchor24" UsedConditions="" LocalConditions="" /><IndexLink Title="Example Using the Flame Length Probabilities Approach" Link="/Content/06-Risk-Assessment/risk_original/RiskAssessNetValueChange3.htm#kanchor1194" UsedConditions="" LocalConditions="" /></Links><SeeAlsoLinks /><IndexControlLinks /><SortAsLinks /></IndexEntry><IndexEntry Term="overview"><Entries /><Links><IndexLink Title="Values at Risk" Link="/Content/06-Risk-Assessment/risk_original/RiskAssessNetValueChange.htm#kanchor1244" UsedConditions="" LocalConditions="" /></Links><SeeAlsoLinks /><IndexControlLinks /><SortAsLinks /></IndexEntry><IndexEntry Term="parameter"><Entries><IndexEntry Term="explanation of"><Entries /><Links><IndexLink Title="Understanding the Net Value Change Parameter" Link="/Content/06-Risk-Assessment/risk_original/RiskAssessNetValueChange4.htm#kanchor413" UsedConditions="" LocalConditions="" /></Links><SeeAlsoLinks /><IndexControlLinks /><SortAsLinks /></IndexEntry></Entries><Links /><SeeAlsoLinks /><IndexControlLinks /><SortAsLinks /></IndexEntry><IndexEntry Term="relative"><Entries><IndexEntry Term="definition"><Entries /><Links><IndexLink Title="Risk Assessment Glossary" Link="/Content/06-Risk-Assessment/risk_original/RiskAssessGlossary.htm#kanchor26" UsedConditions="" LocalConditions="" /></Links><SeeAlsoLinks /><IndexControlLinks /><SortAsLinks /></IndexEntry><IndexEntry Term="worst-case flame length risk assessments and"><Entries /><Links><IndexLink Title="Example Using the Worst-Case Flame Length Approach" Link="/Content/06-Risk-Assessment/risk_original/RiskAssessNetValueChange2.htm#kanchor517" UsedConditions="" LocalConditions="" /></Links><SeeAlsoLinks /><IndexControlLinks /><SortAsLinks /></IndexEntry></Entries><Links><IndexLink Title="Values at Risk" Link="/Content/06-Risk-Assessment/risk_original/RiskAssessNetValueChange.htm#kanchor1244" UsedConditions="" LocalConditions="" /></Links><SeeAlsoLinks /><IndexControlLinks /><SortAsLinks /></IndexEntry><IndexEntry Term="worst-case flame length example"><Entries /><Links><IndexLink Title="Example Using the Worst-Case Flame Length Approach" Link="/Content/06-Risk-Assessment/risk_original/RiskAssessNetValueChange2.htm#kanchor518" UsedConditions="" LocalConditions="" /></Links><SeeAlsoLinks /><IndexControlLinks /><SortAsLinks /></IndexEntry></Entries><Links /><SeeAlsoLinks /><IndexControlLinks /><SortAsLinks /></IndexEntry><IndexEntry Term="new features in IFTDSS"><Entries /><Links><IndexLink Title="What's New" Link="/Content/01-Front-Matter/WhatsNew.htm#kanchor540" UsedConditions="" LocalConditions="" /></Links><SeeAlsoLinks /><IndexControlLinks /><SortAsLinks /></IndexEntry><IndexEntry Term="NEXUS"><Entries><IndexEntry Term="IFTDSS and"><Entries /><Links><IndexLink Title="IFTDSS Compared with Other Systems" Link="/Content/11-Comparing-IFTDSS/IFTCompare.htm#kanchor272" UsedConditions="" LocalConditions="" /></Links><SeeAlsoLinks /><IndexControlLinks /><SortAsLinks /></IndexEntry><IndexEntry Term="surface fire behavior on flat terrain"><Entries /><Links><IndexLink Title="Surface Fire Behavior on Flat Terrain" Link="/Content/11-Comparing-IFTDSS/IFTCompareApp1.htm#kanchor988" UsedConditions="" LocalConditions="" /></Links><SeeAlsoLinks /><IndexControlLinks /><SortAsLinks /></IndexEntry><IndexEntry Term="surface fire behavior on slopes"><Entries /><Links><IndexLink Title="Surface Fire Behavior on a Slope" Link="/Content/11-Comparing-IFTDSS/IFTCompareApp2.htm#kanchor1173" UsedConditions="" LocalConditions="" /></Links><SeeAlsoLinks /><IndexControlLinks /><SortAsLinks /></IndexEntry></Entries><Links /><SeeAlsoLinks /><IndexControlLinks /><SortAsLinks /></IndexEntry><IndexEntry Term="NH3 (parameter)"><Entries><IndexEntry Term="FEPS input"><Entries /><Links><IndexLink Title="Input Parameters—Consumption and Emissions Data" Link="/Content/08-FERA-Tools/FERA-FEPS-In-Consumption.htm#kanchor215" UsedConditions="" LocalConditions="" /></Links><SeeAlsoLinks /><IndexControlLinks /><SortAsLinks /></IndexEntry><IndexEntry Term="FEPS output"><Entries /><Links><IndexLink Title="Output Parameters—Hourly Consumption and Emissions Data" Link="/Content/08-FERA-Tools/FERA-FEPS-Out-Consumption.htm#kanchor395" UsedConditions="" LocalConditions="" /></Links><SeeAlsoLinks /><IndexControlLinks /><SortAsLinks /></IndexEntry></Entries><Links /><SeeAlsoLinks /><IndexControlLinks /><SortAsLinks /></IndexEntry><IndexEntry Term="nitrogen oxides"><Entries><IndexEntry Term="FEPS input"><Entries /><Links><IndexLink Title="Input Parameters—Consumption and Emissions Data" Link="/Content/08-FERA-Tools/FERA-FEPS-In-Consumption.htm#kanchor216" UsedConditions="" LocalConditions="" /></Links><SeeAlsoLinks /><IndexControlLinks /><SortAsLinks /></IndexEntry></Entries><Links /><SeeAlsoLinks /><IndexControlLinks /><SortAsLinks /></IndexEntry></Entries></IndexEntry></CatapultTargetIndex>