<?xml version="1.0" encoding="utf-8"?><index><stem n="fireguard"><phr n="fireguard"><ent r="7" t="3" w="466" /><ent r="9" t="14" w="1369" /><ent r="9" t="15" w="451" /><ent r="7" t="17" w="34" /><ent r="7" t="36" w="113" /><ent r="6" t="41" w="991" /><ent r="8" t="43" w="228" /><ent r="7" t="47" w="30" /><ent r="7" t="60" w="304" /><ent r="8" t="64" w="105" /><ent r="7" t="71" w="44" /><ent r="5" t="72" w="347" /><ent r="5" t="77" w="471" /><ent r="8" t="80" w="132" /><ent r="8" t="82" w="147" /><ent r="7" t="83" w="306" /><ent r="10" t="84" w="234" /><ent r="8" t="87" w="44" /><ent r="7" t="93" w="265" /><ent r="5" t="95" w="356" /><ent r="8" t="101" w="126" /><ent r="8" t="107" w="228" /><ent r="7" t="166" w="831" /><ent r="10" t="175" w="592" /><ent r="11" t="189" w="314" /><ent r="8" t="196" w="104" /><ent r="7" t="197" w="534" /><ent r="7" t="198" w="1069" /><ent r="7" t="201" w="119" /><ent r="8" t="208" w="55" /><ent r="8" t="210" w="104" /><ent r="7" t="211" w="30" /><ent r="7" t="212" w="514" /><ent r="7" t="217" w="119" /><ent r="10" t="218" w="182" /><ent r="7" t="219" w="808" /><ent r="7" t="220" w="110" /><ent r="7" t="224" w="62" /><ent r="7" t="226" w="90" /><ent r="7" t="230" w="967" /><ent r="8" t="307" w="498" /><ent r="8" t="310" w="430" /><ent r="8" t="312" w="501" /><ent r="5" t="346" w="367" /><ent r="5" t="349" w="1397" /><ent r="9" t="352" w="300" /><ent r="7" t="353" w="225" /><ent r="7" t="354" w="221" /><ent r="7" t="365" w="287" /><ent r="8" t="371" w="576" /><ent r="10" t="372" w="666" /><ent r="7" t="373" w="315" /><ent r="7" t="374" w="36" /><ent r="7" t="376" w="190" /><ent r="10" t="378" w="482" /><ent r="10" t="382" w="488" /><ent r="8" t="399" w="534" /><ent r="5" t="400" w="223" /><ent r="5" t="401" w="59" /><ent r="5" t="402" w="46" /><ent r="5" t="403" w="40" /><ent r="5" t="404" w="38" /><ent r="5" t="405" w="45" /><ent r="8" t="406" w="313" /><ent r="7" t="440" w="331" /></phr></stem><stem n="firebreak"><phr n="firebreak"><ent r="7" t="3" w="467" /><ent r="9" t="14" w="1370" /><ent r="9" t="15" w="452" /><ent r="7" t="17" w="35" /><ent r="7" t="36" w="114" /><ent r="6" t="41" w="992" /><ent r="8" t="43" w="229" /><ent r="7" t="47" w="31" /><ent r="7" t="60" w="305" /><ent r="8" t="64" w="106" /><ent r="7" t="71" w="45" /><ent r="5" t="72" w="348" /><ent r="5" t="77" w="472" /><ent r="8" t="80" w="133" /><ent r="8" t="82" w="148" /><ent r="7" t="83" w="307" /><ent r="10" t="84" w="235" /><ent r="8" t="87" w="45" /><ent r="7" t="93" w="266" /><ent r="5" t="95" w="357" /><ent r="8" t="101" w="127" /><ent r="8" t="107" w="229" /><ent r="7" t="166" w="832" /><ent r="10" t="175" w="593" /><ent r="11" t="189" w="315" /><ent r="8" t="196" w="105" /><ent r="7" t="197" w="535" /><ent r="7" t="198" w="1070" /><ent r="7" t="201" w="120" /><ent r="8" t="208" w="56" /><ent r="8" t="210" w="105" /><ent r="7" t="211" w="31" /><ent r="7" t="212" w="515" /><ent r="7" t="217" w="120" /><ent r="10" t="218" w="183" /><ent r="7" t="219" w="809" /><ent r="7" t="220" w="111" /><ent r="7" t="224" w="63" /><ent r="7" t="226" w="91" /><ent r="7" t="230" w="968" /><ent r="8" t="307" w="499" /><ent r="8" t="310" w="431" /><ent r="8" t="312" w="502" /><ent r="5" t="346" w="368" /><ent r="5" t="349" w="1398" /><ent r="9" t="352" w="301" /><ent r="7" t="353" w="226" /><ent r="7" t="354" w="222" /><ent r="7" t="365" w="288" /><ent r="8" t="371" w="577" /><ent r="10" t="372" w="667" /><ent r="7" t="373" w="316" /><ent r="7" t="374" w="37" /><ent r="7" t="376" w="191" /><ent r="10" t="378" w="483" /><ent r="10" t="382" w="489" /><ent r="8" t="399" w="535" /><ent r="5" t="400" w="224" /><ent r="5" t="401" w="60" /><ent r="5" t="402" w="47" /><ent r="5" t="403" w="41" /><ent r="5" t="404" w="39" /><ent r="5" t="405" w="46" /><ent r="8" t="406" w="314" /><ent r="7" t="440" w="332" /></phr></stem><stem n="trip"><phr n="trip"><ent r="7" t="3" w="468" /><ent r="9" t="14" w="1371" /><ent r="9" t="15" w="453" /><ent r="7" t="17" w="36" /><ent r="7" t="36" w="115" /><ent r="6" t="41" w="993" /><ent r="8" t="43" w="230" /><ent r="7" t="47" w="32" /><ent r="7" t="60" w="306" /><ent r="8" t="64" w="107" /><ent r="7" t="71" w="46" /><ent r="5" t="72" w="349" /><ent r="5" t="77" w="473" /><ent r="8" t="80" w="134" /><ent r="8" t="82" w="149" /><ent r="7" t="83" w="308" /><ent r="10" t="84" w="236" /><ent r="8" t="87" w="46" /><ent r="7" t="93" w="267" /><ent r="5" t="95" w="358" /><ent r="8" t="101" w="128" /><ent r="8" t="107" w="230" /><ent r="7" t="166" w="833" /><ent r="10" t="175" w="594" /><ent r="11" t="189" w="316" /><ent r="8" t="196" w="106" /><ent r="7" t="197" w="536" /><ent r="7" t="198" w="1071" /><ent r="7" t="201" w="121" /><ent r="8" t="208" w="57" /><ent r="8" t="210" w="106" /><ent r="7" t="211" w="32" /><ent r="7" t="212" w="516" /><ent r="7" t="217" w="121" /><ent r="10" t="218" w="184" /><ent r="7" t="219" w="810" /><ent r="7" t="220" w="112" /><ent r="7" t="224" w="64" /><ent r="7" t="226" w="92" /><ent r="7" t="230" w="969" /><ent r="8" t="307" w="500" /><ent r="8" t="310" w="432" /><ent r="8" t="312" w="503" /><ent r="5" t="346" w="369" /><ent r="5" t="349" w="1399" /><ent r="9" t="352" w="302" /><ent r="7" t="353" w="227" /><ent r="7" t="354" w="223" /><ent r="7" t="365" w="289" /><ent r="8" t="371" w="578" /><ent r="10" t="372" w="668" /><ent r="7" t="373" w="317" /><ent r="7" t="374" w="38" /><ent r="7" t="376" w="192" /><ent r="10" t="378" w="484" /><ent r="10" t="382" w="490" /><ent r="8" t="399" w="536" /><ent r="5" t="400" w="225" /><ent r="5" t="401" w="61" /><ent r="5" t="402" w="48" /><ent r="5" t="403" w="42" /><ent r="5" t="404" w="40" /><ent r="5" t="405" w="47" /><ent r="8" t="406" w="315" /><ent r="7" t="440" w="333" /></phr></stem><stem n="open"><phr n="open"><ent r="7" t="3" w="469" /><ent r="4" t="5" w="282" /><ent r="3" t="9" w="186" /><ent r="9" t="14" w="1372" /><ent r="9" t="15" w="454" /><ent r="7" t="17" w="37" /><ent r="3" t="31" w="372" /><ent r="3" t="31" w="386" /><ent r="7" t="36" w="116" /><ent r="6" t="41" w="994" /><ent r="8" t="43" w="231" /><ent r="7" t="47" w="33" /><ent r="3" t="56" w="56" /><ent r="3" t="57" w="271" /><ent r="7" t="60" w="307" /><ent r="8" t="64" w="108" /><ent r="7" t="71" w="47" /><ent r="5" t="72" w="350" /><ent r="5" t="74" w="58" /><ent r="5" t="74" w="73" /><ent r="5" t="77" w="474" /><ent r="8" t="80" w="135" /><ent r="8" t="82" w="150" /><ent r="7" t="83" w="309" /><ent r="10" t="84" w="237" /><ent r="8" t="87" w="47" /><ent r="7" t="93" w="268" /><ent r="5" t="95" w="359" /><ent r="5" t="97" w="52" /><ent r="8" t="101" w="129" /><ent r="7" t="105" w="526" /><ent r="8" t="107" w="231" /><ent r="6" t="109" w="556" /><ent r="6" t="113" w="98" /><ent r="3" t="128" w="21" /><ent r="4" t="128" w="29" /><ent r="3" t="137" w="26" /><ent r="3" t="146" w="16" /><ent r="4" t="149" w="11" /><ent r="6" t="151" w="30" /><ent r="6" t="159" w="177" /><ent r="7" t="166" w="834" /><ent r="10" t="175" w="595" /><ent r="3" t="182" w="76" /><ent r="11" t="189" w="317" /><ent r="3" t="195" w="1094" /><ent r="8" t="196" w="107" /><ent r="7" t="197" w="537" /><ent r="7" t="198" w="1072" /><ent r="4" t="199" w="131" /><ent r="7" t="201" w="122" /><ent r="8" t="208" w="58" /><ent r="3" t="209" w="1094" /><ent r="8" t="210" w="107" /><ent r="7" t="211" w="33" /><ent r="4" t="211" w="986" /><ent r="3" t="211" w="1581" /><ent r="7" t="212" w="517" /><ent r="3" t="213" w="1107" /><ent r="4" t="213" w="1485" /><ent r="7" t="217" w="122" /><ent r="10" t="218" w="185" /><ent r="7" t="219" w="811" /><ent r="7" t="220" w="113" /><ent r="7" t="224" w="65" /><ent r="7" t="226" w="93" /><ent r="6" t="230" w="672" /><ent r="3" t="230" w="708" /><ent r="3" t="230" w="855" /><ent r="6" t="230" w="912" /><ent r="7" t="230" w="970" /><ent r="5" t="237" w="19" /><ent r="3" t="256" w="23" /><ent r="3" t="286" w="202" /><ent r="4096" t="304" w="53" /><ent r="4" t="304" w="372" /><ent r="8" t="307" w="501" /><ent r="8" t="310" w="433" /><ent r="8" t="312" w="504" /><ent r="5" t="346" w="370" /><ent r="5" t="349" w="1400" /><ent r="9" t="352" w="303" /><ent r="7" t="353" w="228" /><ent r="7" t="354" w="224" /><ent r="3" t="357" w="32" /><ent r="3" t="357" w="38" /><ent r="4" t="357" w="1711" /><ent r="6" t="360" w="717" /><ent r="6" t="360" w="724" /><ent r="4096" t="360" w="2256" /><ent r="6" t="360" w="2262" /><ent r="6" t="360" w="2268" /><ent r="7" t="365" w="290" /><ent r="8" t="371" w="579" /><ent r="10" t="372" w="669" /><ent r="7" t="373" w="318" /><ent r="7" t="374" w="39" /><ent r="7" t="376" w="193" /><ent r="10" t="378" w="485" /><ent r="10" t="382" w="491" /><ent r="8" t="399" w="537" /><ent r="5" t="400" w="226" /><ent r="6" t="400" w="368" /><ent r="5" t="401" w="62" /><ent r="6" t="401" w="217" /><ent r="5" t="402" w="49" /><ent r="6" t="402" w="215" /><ent r="5" t="403" w="43" /><ent r="5" t="404" w="41" /><ent r="5" t="405" w="48" /><ent r="8" t="406" w="316" /><ent r="6" t="412" w="309" /><ent r="6" t="413" w="369" /><ent r="6" t="414" w="317" /><ent r="7" t="440" w="334" /><ent r="9" t="452" w="120" /><ent r="5" t="452" w="125" /><ent r="5" t="452" w="143" /></phr><phr n="opens"><ent r="3" t="11" w="33" /><ent r="4" t="20" w="234" /><ent r="3" t="21" w="455" /><ent r="3" t="25" w="344" /><ent r="3" t="30" w="43" /><ent r="3" t="181" w="94" /><ent r="3" t="195" w="950" /><ent r="3" t="209" w="950" /><ent r="3" t="213" w="964" /><ent r="3" t="235" w="133" /><ent r="6" t="237" w="32" /><ent r="4" t="300" w="443" /></phr><phr n="opening"><ent r="3" t="30" w="102" /><ent r="6" t="256" w="576" /><ent r="3" t="306" w="381" /><ent r="3" t="357" w="48" /></phr><phr n="opened"><ent r="3" t="128" w="38" /><ent r="3" t="199" w="106" /><ent r="3" t="213" w="106" /><ent r="3" t="452" w="19" /></phr><phr n="openings"><ent r="7" t="349" w="418" /><ent r="5" t="349" w="481" /><ent r="8" t="349" w="1770" /><ent r="6" t="360" w="1152" /><ent r="8" t="360" w="1383" /></phr></stem><stem n="land"><phr n="land"><ent r="7" t="3" w="470" /><ent r="7" t="6" w="583" /><ent r="9" t="6" w="595" /><ent r="9" t="6" w="602" /><ent r="7" t="6" w="606" /><ent r="8" t="12" w="275" /><ent r="10" t="12" w="287" /><ent r="10" t="12" w="294" /><ent r="8" t="12" w="298" /><ent r="8" t="13" w="376" /><ent r="10" t="13" w="388" /><ent r="10" t="13" w="395" /><ent r="8" t="13" w="399" /><ent r="7" t="14" w="232" /><ent r="9" t="14" w="244" /><ent r="9" t="14" w="251" /><ent r="7" t="14" w="255" /><ent r="9" t="14" w="1373" /><ent r="9" t="14" w="1433" /><ent r="7" t="15" w="316" /><ent r="9" t="15" w="455" /><ent r="10" t="15" w="884" /><ent r="12" t="15" w="1038" /><ent r="14" t="15" w="1050" /><ent r="14" t="15" w="1057" /><ent r="12" t="15" w="1061" /><ent r="8" t="15" w="1096" /><ent r="8" t="15" w="1166" /><ent r="8" t="15" w="1851" /><ent r="8" t="15" w="1933" /><ent r="9" t="16" w="991" /><ent r="7" t="17" w="38" /><ent r="9" t="17" w="461" /><ent r="11" t="17" w="473" /><ent r="11" t="17" w="480" /><ent r="9" t="17" w="484" /><ent r="7" t="17" w="2932" /><ent r="10" t="17" w="3326" /><ent r="8" t="17" w="3413" /><ent r="8" t="17" w="3483" /><ent r="7" t="20" w="188" /><ent r="9" t="20" w="200" /><ent r="9" t="20" w="207" /><ent r="7" t="20" w="211" /><ent r="8" t="22" w="201" /><ent r="10" t="22" w="213" /><ent r="10" t="22" w="220" /><ent r="8" t="22" w="224" /><ent r="8" t="24" w="272" /><ent r="10" t="24" w="284" /><ent r="10" t="24" w="291" /><ent r="8" t="24" w="295" /><ent r="11" t="24" w="973" /><ent r="4" t="26" w="98" /><ent r="8" t="27" w="367" /><ent r="10" t="27" w="379" /><ent r="10" t="27" w="386" /><ent r="8" t="27" w="390" /><ent r="3" t="32" w="11" /><ent r="8" t="35" w="565" /><ent r="7" t="36" w="117" /><ent r="10" t="37" w="975" /><ent r="7" t="38" w="547" /><ent r="9" t="38" w="559" /><ent r="9" t="38" w="566" /><ent r="7" t="38" w="570" /><ent r="12" t="39" w="660" /><ent r="7" t="41" w="234" /><ent r="9" t="41" w="246" /><ent r="9" t="41" w="253" /><ent r="7" t="41" w="257" /><ent r="6" t="41" w="995" /><ent r="7" t="42" w="243" /><ent r="9" t="42" w="255" /><ent r="9" t="42" w="262" /><ent r="7" t="42" w="266" /><ent r="8" t="43" w="232" /><ent r="7" t="47" w="34" /><ent r="8" t="48" w="174" /><ent r="10" t="48" w="186" /><ent r="10" t="48" w="193" /><ent r="8" t="48" w="197" /><ent r="5" t="49" w="609" /><ent r="3" t="53" w="74" /><ent r="7" t="60" w="230" /><ent r="9" t="60" w="242" /><ent r="9" t="60" w="249" /><ent r="7" t="60" w="253" /><ent r="7" t="60" w="308" /><ent r="8" t="64" w="109" /><ent r="8" t="64" w="283" /><ent r="10" t="64" w="295" /><ent r="10" t="64" w="302" /><ent r="8" t="64" w="306" /><ent r="7" t="65" w="171" /><ent r="9" t="65" w="183" /><ent r="9" t="65" w="190" /><ent r="7" t="65" w="194" /><ent r="3" t="70" w="11" /><ent r="7" t="71" w="48" /><ent r="5" t="72" w="351" /><ent r="5" t="77" w="475" /><ent r="4" t="78" w="110" /><ent r="8" t="80" w="136" /><ent r="8" t="82" w="151" /><ent r="7" t="83" w="230" /><ent r="9" t="83" w="242" /><ent r="9" t="83" w="249" /><ent r="7" t="83" w="253" /><ent r="7" t="83" w="310" /><ent r="10" t="84" w="238" /><ent r="8" t="87" w="48" /><ent r="8" t="87" w="236" /><ent r="10" t="87" w="248" /><ent r="10" t="87" w="255" /><ent r="8" t="87" w="259" /><ent r="7" t="88" w="179" /><ent r="9" t="88" w="191" /><ent r="9" t="88" w="198" /><ent r="7" t="88" w="202" /><ent r="7" t="93" w="269" /><ent r="5" t="95" w="360" /><ent r="8" t="101" w="130" /><ent r="7" t="106" w="582" /><ent r="8" t="107" w="232" /><ent r="8" t="112" w="475" /><ent r="3" t="114" w="326" /><ent r="7" t="116" w="174" /><ent r="9" t="116" w="186" /><ent r="9" t="116" w="193" /><ent r="7" t="116" w="197" /><ent r="7" t="125" w="180" /><ent r="7" t="163" w="57" /><ent r="7" t="164" w="55" /><ent r="9" t="165" w="499" /><ent r="7" t="165" w="529" /><ent r="7" t="166" w="291" /><ent r="9" t="166" w="303" /><ent r="9" t="166" w="310" /><ent r="7" t="166" w="314" /><ent r="5" t="166" w="653" /><ent r="7" t="166" w="835" /><ent r="5" t="170" w="94" /><ent r="5" t="170" w="136" /><ent r="3" t="170" w="156" /><ent r="5" t="171" w="212" /><ent r="5" t="171" w="247" /><ent r="5" t="172" w="194" /><ent r="7" t="172" w="425" /><ent r="5" t="172" w="455" /><ent r="7" t="173" w="99" /><ent r="5" t="173" w="129" /><ent r="5" t="174" w="105" /><ent r="10" t="175" w="596" /><ent r="8" t="175" w="680" /><ent r="8" t="175" w="715" /><ent r="10" t="175" w="871" /><ent r="12" t="175" w="883" /><ent r="12" t="175" w="890" /><ent r="10" t="175" w="894" /><ent r="8" t="175" w="937" /><ent r="6" t="175" w="960" /><ent r="8" t="180" w="209" /><ent r="10" t="180" w="221" /><ent r="10" t="180" w="228" /><ent r="8" t="180" w="232" /><ent r="7" t="183" w="174" /><ent r="9" t="183" w="186" /><ent r="9" t="183" w="193" /><ent r="7" t="183" w="197" /><ent r="7" t="186" w="183" /><ent r="9" t="186" w="195" /><ent r="9" t="186" w="202" /><ent r="7" t="186" w="206" /><ent r="11" t="189" w="318" /><ent r="7" t="190" w="628" /><ent r="9" t="190" w="640" /><ent r="9" t="190" w="647" /><ent r="7" t="190" w="651" /><ent r="7" t="191" w="200" /><ent r="9" t="191" w="212" /><ent r="9" t="191" w="219" /><ent r="7" t="191" w="223" /><ent r="7" t="192" w="203" /><ent r="9" t="192" w="215" /><ent r="9" t="192" w="222" /><ent r="7" t="192" w="226" /><ent r="7" t="193" w="231" /><ent r="9" t="193" w="243" /><ent r="9" t="193" w="250" /><ent r="7" t="193" w="254" /><ent r="8" t="194" w="226" /><ent r="10" t="194" w="238" /><ent r="10" t="194" w="245" /><ent r="8" t="194" w="249" /><ent r="7" t="195" w="262" /><ent r="9" t="195" w="274" /><ent r="9" t="195" w="281" /><ent r="7" t="195" w="285" /><ent r="8" t="196" w="108" /><ent r="7" t="196" w="775" /><ent r="9" t="196" w="787" /><ent r="9" t="196" w="794" /><ent r="7" t="196" w="798" /><ent r="7" t="197" w="207" /><ent r="9" t="197" w="219" /><ent r="9" t="197" w="226" /><ent r="7" t="197" w="230" /><ent r="3" t="197" w="394" /><ent r="7" t="197" w="538" /><ent r="7" t="198" w="314" /><ent r="9" t="198" w="326" /><ent r="9" t="198" w="333" /><ent r="7" t="198" w="337" /><ent r="5" t="198" w="942" /><ent r="7" t="198" w="1073" /><ent r="5" t="198" w="1144" /><ent r="7" t="200" w="104" /><ent r="5" t="200" w="134" /><ent r="7" t="200" w="374" /><ent r="9" t="200" w="386" /><ent r="9" t="200" w="393" /><ent r="7" t="200" w="397" /><ent r="7" t="201" w="123" /><ent r="8" t="204" w="659" /><ent r="10" t="204" w="671" /><ent r="10" t="204" w="678" /><ent r="8" t="204" w="682" /><ent r="7" t="205" w="200" /><ent r="9" t="205" w="212" /><ent r="9" t="205" w="219" /><ent r="7" t="205" w="223" /><ent r="7" t="206" w="203" /><ent r="9" t="206" w="215" /><ent r="9" t="206" w="222" /><ent r="7" t="206" w="226" /><ent r="7" t="207" w="251" /><ent r="9" t="207" w="263" /><ent r="9" t="207" w="270" /><ent r="7" t="207" w="274" /><ent r="8" t="208" w="59" /><ent r="8" t="208" w="314" /><ent r="10" t="208" w="326" /><ent r="10" t="208" w="333" /><ent r="8" t="208" w="337" /><ent r="7" t="209" w="262" /><ent r="9" t="209" w="274" /><ent r="9" t="209" w="281" /><ent r="7" t="209" w="285" /><ent r="8" t="210" w="108" /><ent r="7" t="210" w="923" /><ent r="9" t="210" w="935" /><ent r="9" t="210" w="942" /><ent r="7" t="210" w="946" /><ent r="7" t="211" w="34" /><ent r="7" t="211" w="360" /><ent r="9" t="211" w="372" /><ent r="9" t="211" w="379" /><ent r="7" t="211" w="383" /><ent r="4" t="211" w="980" /><ent r="5" t="211" w="1050" /><ent r="5" t="211" w="1198" /><ent r="5" t="211" w="1267" /><ent r="7" t="212" w="207" /><ent r="9" t="212" w="219" /><ent r="9" t="212" w="226" /><ent r="7" t="212" w="230" /><ent r="3" t="212" w="377" /><ent r="7" t="212" w="518" /><ent r="7" t="213" w="328" /><ent r="9" t="213" w="340" /><ent r="9" t="213" w="347" /><ent r="7" t="213" w="351" /><ent r="7" t="214" w="99" /><ent r="5" t="214" w="129" /><ent r="7" t="214" w="377" /><ent r="9" t="214" w="389" /><ent r="9" t="214" w="396" /><ent r="7" t="214" w="400" /><ent r="7" t="217" w="123" /><ent r="10" t="218" w="186" /><ent r="7" t="219" w="812" /><ent r="7" t="220" w="114" /><ent r="7" t="222" w="198" /><ent r="9" t="222" w="210" /><ent r="9" t="222" w="217" /><ent r="7" t="222" w="221" /><ent r="7" t="223" w="203" /><ent r="9" t="223" w="215" /><ent r="9" t="223" w="222" /><ent r="7" t="223" w="226" /><ent r="7" t="224" w="66" /><ent r="7" t="224" w="355" /><ent r="9" t="224" w="367" /><ent r="9" t="224" w="374" /><ent r="7" t="224" w="378" /><ent r="7" t="226" w="94" /><ent r="8" t="229" w="228" /><ent r="10" t="229" w="240" /><ent r="10" t="229" w="247" /><ent r="8" t="229" w="251" /><ent r="7" t="230" w="971" /><ent r="7" t="236" w="535" /><ent r="9" t="236" w="547" /><ent r="9" t="236" w="554" /><ent r="7" t="236" w="558" /><ent r="10" t="241" w="222" /><ent r="12" t="241" w="234" /><ent r="12" t="241" w="241" /><ent r="10" t="241" w="245" /><ent r="7" t="242" w="109" /><ent r="7" t="243" w="236" /><ent r="9" t="243" w="248" /><ent r="9" t="243" w="255" /><ent r="7" t="243" w="259" /><ent r="8" t="244" w="66" /><ent r="7" t="245" w="52" /><ent r="7" t="246" w="20" /><ent r="7" t="249" w="43" /><ent r="7" t="250" w="200" /><ent r="9" t="250" w="212" /><ent r="9" t="250" w="219" /><ent r="7" t="250" w="223" /><ent r="10" t="253" w="616" /><ent r="8" t="254" w="378" /><ent r="7" t="256" w="192" /><ent r="7" t="256" w="1018" /><ent r="9" t="256" w="1030" /><ent r="9" t="256" w="1037" /><ent r="7" t="256" w="1041" /><ent r="7" t="257" w="43" /><ent r="8" t="258" w="477" /><ent r="3" t="259" w="28" /><ent r="7" t="259" w="235" /><ent r="7" t="260" w="460" /><ent r="9" t="263" w="709" /><ent r="10" t="264" w="697" /><ent r="7" t="265" w="49" /><ent r="7" t="265" w="79" /><ent r="7" t="265" w="86" /><ent r="7" t="267" w="23" /><ent r="7" t="267" w="53" /><ent r="7" t="267" w="60" /><ent r="7" t="268" w="71" /><ent r="7" t="268" w="361" /><ent r="7" t="268" w="368" /><ent r="7" t="270" w="73" /><ent r="7" t="271" w="147" /><ent r="9" t="272" w="427" /><ent r="9" t="273" w="419" /><ent r="9" t="274" w="429" /><ent r="9" t="275" w="429" /><ent r="7" t="276" w="49" /><ent r="7" t="276" w="79" /><ent r="7" t="276" w="86" /><ent r="7" t="278" w="23" /><ent r="7" t="278" w="53" /><ent r="7" t="278" w="60" /><ent r="7" t="279" w="71" /><ent r="7" t="279" w="361" /><ent r="7" t="279" w="368" /><ent r="7" t="280" w="64" /><ent r="7" t="283" w="50" /><ent r="7" t="284" w="130" /><ent r="7" t="285" w="64" /><ent r="7" t="287" w="52" /><ent r="8" t="288" w="21" /><ent r="7" t="289" w="72" /><ent r="7" t="293" w="428" /><ent r="5" t="294" w="422" /><ent r="3" t="297" w="118" /><ent r="8" t="297" w="611" /><ent r="6" t="301" w="292" /><ent r="4096" t="301" w="641" /><ent r="6" t="301" w="652" /><ent r="7" t="307" w="407" /><ent r="8" t="307" w="502" /><ent r="8" t="308" w="841" /><ent r="5" t="309" w="51" /><ent r="8" t="310" w="434" /><ent r="8" t="312" w="505" /><ent r="8" t="313" w="526" /><ent r="11" t="314" w="81" /><ent r="8" t="314" w="138" /><ent r="8" t="314" w="145" /><ent r="11" t="315" w="43" /><ent r="8" t="315" w="112" /><ent r="8" t="315" w="119" /><ent r="8" t="316" w="30" /><ent r="8" t="316" w="60" /><ent r="8" t="316" w="67" /><ent r="7" t="321" w="89" /><ent r="7" t="322" w="105" /><ent r="7" t="323" w="84" /><ent r="8" t="324" w="60" /><ent r="10" t="324" w="72" /><ent r="10" t="324" w="79" /><ent r="8" t="324" w="83" /><ent r="8" t="324" w="168" /><ent r="7" t="327" w="82" /><ent r="8" t="328" w="90" /><ent r="10" t="328" w="102" /><ent r="10" t="328" w="109" /><ent r="8" t="328" w="113" /><ent r="7" t="330" w="43" /><ent r="11" t="332" w="65" /><ent r="7" t="334" w="43" /><ent r="7" t="337" w="51" /><ent r="7" t="338" w="158" /><ent r="5" t="346" w="371" /><ent r="7" t="349" w="664" /><ent r="5" t="349" w="1401" /><ent r="9" t="352" w="304" /><ent r="7" t="353" w="229" /><ent r="7" t="354" w="225" /><ent r="4" t="357" w="950" /><ent r="7" t="357" w="3286" /><ent r="8" t="358" w="126" /><ent r="8" t="358" w="332" /><ent r="8" t="358" w="339" /><ent r="8" t="358" w="352" /><ent r="8" t="358" w="359" /><ent r="8" t="360" w="1782" /><ent r="8" t="360" w="1814" /><ent r="8" t="360" w="1821" /><ent r="6" t="360" w="2096" /><ent r="6" t="360" w="2170" /><ent r="6" t="360" w="2211" /><ent r="6" t="360" w="2266" /><ent r="6" t="360" w="2292" /><ent r="8" t="362" w="440" /><ent r="7" t="365" w="291" /><ent r="10" t="367" w="512" /><ent r="12" t="367" w="524" /><ent r="12" t="367" w="531" /><ent r="10" t="367" w="535" /><ent r="8" t="371" w="580" /><ent r="8" t="371" w="688" /><ent r="8" t="371" w="719" /><ent r="8" t="371" w="726" /><ent r="10" t="372" w="670" /><ent r="8" t="372" w="864" /><ent r="10" t="372" w="876" /><ent r="10" t="372" w="883" /><ent r="8" t="372" w="887" /><ent r="7" t="373" w="319" /><ent r="7" t="374" w="40" /><ent r="7" t="374" w="347" /><ent r="9" t="374" w="359" /><ent r="9" t="374" w="366" /><ent r="7" t="374" w="370" /><ent r="7" t="374" w="387" /><ent r="7" t="376" w="194" /><ent r="10" t="377" w="932" /><ent r="12" t="377" w="944" /><ent r="12" t="377" w="951" /><ent r="10" t="377" w="955" /><ent r="6" t="377" w="1203" /><ent r="10" t="378" w="486" /><ent r="10" t="382" w="492" /><ent r="8" t="391" w="679" /><ent r="8" t="391" w="686" /><ent r="10" t="393" w="78" /><ent r="8" t="399" w="142" /><ent r="10" t="399" w="154" /><ent r="10" t="399" w="161" /><ent r="8" t="399" w="165" /><ent r="8" t="399" w="538" /><ent r="5" t="400" w="227" /><ent r="5" t="401" w="63" /><ent r="5" t="402" w="50" /><ent r="5" t="403" w="44" /><ent r="5" t="404" w="42" /><ent r="5" t="405" w="49" /><ent r="8" t="406" w="174" /><ent r="10" t="406" w="186" /><ent r="10" t="406" w="193" /><ent r="8" t="406" w="197" /><ent r="8" t="406" w="317" /><ent r="8" t="409" w="187" /><ent r="10" t="409" w="199" /><ent r="10" t="409" w="206" /><ent r="8" t="409" w="210" /><ent r="8" t="421" w="31" /><ent r="10" t="421" w="43" /><ent r="10" t="421" w="50" /><ent r="8" t="421" w="54" /><ent r="7" t="423" w="175" /><ent r="10" t="424" w="713" /><ent r="8" t="425" w="97" /><ent r="7" t="426" w="60" /><ent r="10" t="427" w="75" /><ent r="8" t="428" w="39" /><ent r="8" t="429" w="211" /><ent r="8" t="430" w="143" /><ent r="8" t="430" w="175" /><ent r="8" t="430" w="182" /><ent r="6" t="430" w="187" /><ent r="6" t="430" w="213" /><ent r="6" t="430" w="231" /><ent r="6" t="430" w="254" /><ent r="6" t="438" w="66" /><ent r="7" t="439" w="534" /><ent r="9" t="439" w="546" /><ent r="9" t="439" w="553" /><ent r="7" t="439" w="557" /><ent r="5" t="440" w="153" /><ent r="7" t="440" w="335" /><ent r="8" t="442" w="76" /><ent r="10" t="442" w="298" /><ent r="12" t="442" w="310" /><ent r="12" t="442" w="317" /><ent r="10" t="442" w="321" /><ent r="6" t="442" w="356" /><ent r="6" t="442" w="426" /><ent r="5" t="443" w="131" /><ent r="10" t="445" w="508" /><ent r="12" t="445" w="520" /><ent r="12" t="445" w="527" /><ent r="10" t="445" w="531" /><ent r="6" t="445" w="566" /><ent r="8" t="445" w="598" /><ent r="6" t="445" w="736" /><ent r="8" t="446" w="590" /><ent r="7" t="447" w="763" /><ent r="9" t="447" w="775" /><ent r="9" t="447" w="782" /><ent r="7" t="447" w="786" /><ent r="3" t="448" w="159" /><ent r="3" t="448" w="195" /><ent r="3" t="448" w="575" /><ent r="10" t="451" w="443" /></phr><phr n="lands"><ent r="6" t="301" w="720" /><ent r="4" t="357" w="1862" /><ent r="4" t="357" w="3457" /><ent r="6" t="360" w="726" /><ent r="6" t="416" w="255" /><ent r="6" t="417" w="366" /><ent r="6" t="418" w="292" /></phr></stem><stem n="clear"><phr n="cleared"><ent r="7" t="3" w="471" /><ent r="9" t="14" w="1374" /><ent r="9" t="15" w="456" /><ent r="7" t="17" w="39" /><ent r="7" t="36" w="118" /><ent r="6" t="41" w="996" /><ent r="8" t="43" w="233" /><ent r="7" t="47" w="35" /><ent r="7" t="60" w="309" /><ent r="8" t="64" w="110" /><ent r="7" t="71" w="49" /><ent r="5" t="72" w="352" /><ent r="5" t="77" w="476" /><ent r="8" t="80" w="137" /><ent r="8" t="82" w="152" /><ent r="7" t="83" w="311" /><ent r="10" t="84" w="239" /><ent r="8" t="87" w="49" /><ent r="7" t="93" w="270" /><ent r="5" t="95" w="361" /><ent r="8" t="101" w="131" /><ent r="8" t="107" w="233" /><ent r="7" t="166" w="836" /><ent r="10" t="175" w="597" /><ent r="11" t="189" w="319" /><ent r="8" t="196" w="109" /><ent r="7" t="197" w="539" /><ent r="7" t="198" w="1074" /><ent r="7" t="201" w="124" /><ent r="8" t="208" w="60" /><ent r="8" t="210" w="109" /><ent r="7" t="211" w="35" /><ent r="7" t="212" w="519" /><ent r="7" t="217" w="124" /><ent r="10" t="218" w="187" /><ent r="7" t="219" w="813" /><ent r="7" t="220" w="115" /><ent r="7" t="224" w="67" /><ent r="7" t="226" w="95" /><ent r="7" t="230" w="972" /><ent r="8" t="307" w="503" /><ent r="8" t="310" w="435" /><ent r="8" t="312" w="506" /><ent r="5" t="346" w="372" /><ent r="5" t="349" w="1402" /><ent r="9" t="352" w="305" /><ent r="7" t="353" w="230" /><ent r="7" t="354" w="226" /><ent r="7" t="365" w="292" /><ent r="8" t="371" w="581" /><ent r="10" t="372" w="671" /><ent r="7" t="373" w="320" /><ent r="7" t="374" w="41" /><ent r="7" t="376" w="195" /><ent r="10" t="378" w="487" /><ent r="10" t="382" w="493" /><ent r="8" t="399" w="539" /><ent r="5" t="400" w="228" /><ent r="5" t="401" w="64" /><ent r="5" t="402" w="51" /><ent r="5" t="403" w="45" /><ent r="5" t="404" w="43" /><ent r="5" t="405" w="50" /><ent r="8" t="406" w="318" /><ent r="7" t="440" w="336" /></phr><phr n="clear"><ent r="3" t="77" w="178" /><ent r="3" t="78" w="418" /><ent r="3" t="125" w="23" /><ent r="3" t="198" w="871" /><ent r="3" t="202" w="384" /><ent r="3" t="211" w="946" /><ent r="3" t="215" w="384" /><ent r="6" t="360" w="1760" /><ent r="6" t="360" w="1916" /><ent r="6" t="360" w="2016" /></phr><phr n="clearly"><ent r="4" t="123" w="80" /><ent r="3" t="139" w="112" /></phr></stem></index>